{
  "openapi": "3.0.1",
  "info": {
    "title": "AFECOR Order System API",
    "description": "API para el sistema de pedidos de productos agroquímicos",
    "version": "v1"
  },
  "paths": {
    "/api/Clientes": {
      "get": {
        "tags": [
          "Clientes"
        ],
        "responses": {
          "200": {
            "description": "OK",
            "content": {
              "text/plain": {
                "schema": {
                  "type": "array",
                  "items": {
                    "$ref": "#/components/schemas/ClienteDto"
                  }
                }
              },
              "application/json": {
                "schema": {
                  "type": "array",
                  "items": {
                    "$ref": "#/components/schemas/ClienteDto"
                  }
                }
              },
              "text/json": {
                "schema": {
                  "type": "array",
                  "items": {
                    "$ref": "#/components/schemas/ClienteDto"
                  }
                }
              }
            }
          }
        }
      }
    },
    "/api/Clientes/{id}": {
      "get": {
        "tags": [
          "Clientes"
        ],
        "parameters": [
          {
            "name": "id",
            "in": "path",
            "required": true,
            "schema": {
              "type": "integer",
              "format": "int32"
            }
          }
        ],
        "responses": {
          "200": {
            "description": "OK",
            "content": {
              "text/plain": {
                "schema": {
                  "$ref": "#/components/schemas/ClienteDto"
                }
              },
              "application/json": {
                "schema": {
                  "$ref": "#/components/schemas/ClienteDto"
                }
              },
              "text/json": {
                "schema": {
                  "$ref": "#/components/schemas/ClienteDto"
                }
              }
            }
          }
        }
      }
    },
    "/api/Pedidos": {
      "get": {
        "tags": [
          "Pedidos"
        ],
        "responses": {
          "200": {
            "description": "OK",
            "content": {
              "text/plain": {
                "schema": {
                  "type": "array",
                  "items": {
                    "$ref": "#/components/schemas/PedidoDto"
                  }
                }
              },
              "application/json": {
                "schema": {
                  "type": "array",
                  "items": {
                    "$ref": "#/components/schemas/PedidoDto"
                  }
                }
              },
              "text/json": {
                "schema": {
                  "type": "array",
                  "items": {
                    "$ref": "#/components/schemas/PedidoDto"
                  }
                }
              }
            }
          }
        }
      },
      "post": {
        "tags": [
          "Pedidos"
        ],
        "requestBody": {
          "content": {
            "application/json": {
              "schema": {
                "$ref": "#/components/schemas/CreatePedidoDto"
              }
            },
            "text/json": {
              "schema": {
                "$ref": "#/components/schemas/CreatePedidoDto"
              }
            },
            "application/*+json": {
              "schema": {
                "$ref": "#/components/schemas/CreatePedidoDto"
              }
            }
          }
        },
        "responses": {
          "200": {
            "description": "OK",
            "content": {
              "text/plain": {
                "schema": {
                  "$ref": "#/components/schemas/PedidoDto"
                }
              },
              "application/json": {
                "schema": {
                  "$ref": "#/components/schemas/PedidoDto"
                }
              },
              "text/json": {
                "schema": {
                  "$ref": "#/components/schemas/PedidoDto"
                }
              }
            }
          }
        }
      }
    },
    "/api/Pedidos/{id}": {
      "get": {
        "tags": [
          "Pedidos"
        ],
        "parameters": [
          {
            "name": "id",
            "in": "path",
            "required": true,
            "schema": {
              "type": "integer",
              "format": "int32"
            }
          }
        ],
        "responses": {
          "200": {
            "description": "OK",
            "content": {
              "text/plain": {
                "schema": {
                  "$ref": "#/components/schemas/PedidoDto"
                }
              },
              "application/json": {
                "schema": {
                  "$ref": "#/components/schemas/PedidoDto"
                }
              },
              "text/json": {
                "schema": {
                  "$ref": "#/components/schemas/PedidoDto"
                }
              }
            }
          }
        }
      },
      "put": {
        "tags": [
          "Pedidos"
        ],
        "parameters": [
          {
            "name": "id",
            "in": "path",
            "required": true,
            "schema": {
              "type": "integer",
              "format": "int32"
            }
          }
        ],
        "requestBody": {
          "content": {
            "application/json": {
              "schema": {
                "$ref": "#/components/schemas/UpdatePedidoDto"
              }
            },
            "text/json": {
              "schema": {
                "$ref": "#/components/schemas/UpdatePedidoDto"
              }
            },
            "application/*+json": {
              "schema": {
                "$ref": "#/components/schemas/UpdatePedidoDto"
              }
            }
          }
        },
        "responses": {
          "200": {
            "description": "OK"
          }
        }
      },
      "delete": {
        "tags": [
          "Pedidos"
        ],
        "parameters": [
          {
            "name": "id",
            "in": "path",
            "required": true,
            "schema": {
              "type": "integer",
              "format": "int32"
            }
          }
        ],
        "responses": {
          "200": {
            "description": "OK"
          }
        }
      }
    },
    "/api/Productos": {
      "get": {
        "tags": [
          "Productos"
        ],
        "responses": {
          "200": {
            "description": "OK",
            "content": {
              "text/plain": {
                "schema": {
                  "type": "array",
                  "items": {
                    "$ref": "#/components/schemas/ProductoDto"
                  }
                }
              },
              "application/json": {
                "schema": {
                  "type": "array",
                  "items": {
                    "$ref": "#/components/schemas/ProductoDto"
                  }
                }
              },
              "text/json": {
                "schema": {
                  "type": "array",
                  "items": {
                    "$ref": "#/components/schemas/ProductoDto"
                  }
                }
              }
            }
          }
        }
      }
    },
    "/api/Productos/{id}": {
      "get": {
        "tags": [
          "Productos"
        ],
        "parameters": [
          {
            "name": "id",
            "in": "path",
            "required": true,
            "schema": {
              "type": "integer",
              "format": "int32"
            }
          }
        ],
        "responses": {
          "200": {
            "description": "OK",
            "content": {
              "text/plain": {
                "schema": {
                  "$ref": "#/components/schemas/ProductoDto"
                }
              },
              "application/json": {
                "schema": {
                  "$ref": "#/components/schemas/ProductoDto"
                }
              },
              "text/json": {
                "schema": {
                  "$ref": "#/components/schemas/ProductoDto"
                }
              }
            }
          }
        }
      }
    },
    "/": {
      "get": {
        "tags": [
          "WebApiOrderSystem"
        ],
        "responses": {
          "200": {
            "description": "OK"
          }
        }
      }
    }
  },
  "components": {
    "schemas": {
      "ClienteDto": {
        "type": "object",
        "properties": {
          "clienteId": {
            "type": "integer",
            "format": "int32"
          },
          "nombre": {
            "type": "string",
            "nullable": true
          },
          "email": {
            "type": "string",
            "nullable": true
          },
          "telefono": {
            "type": "string",
            "nullable": true
          },
          "direccion": {
            "type": "string",
            "nullable": true
          },
          "fechaCreacion": {
            "type": "string",
            "format": "date-time"
          }
        },
        "additionalProperties": false
      },
      "CreateDetallePedidoDto": {
        "required": [
          "cantidad",
          "precioUnitario",
          "productoId"
        ],
        "type": "object",
        "properties": {
          "productoId": {
            "type": "integer",
            "format": "int32"
          },
          "cantidad": {
            "maximum": 2147483647,
            "minimum": 1,
            "type": "integer",
            "format": "int32"
          },
          "precioUnitario": {
            "minimum": 0,01,
            "type": "number",
            "format": "double"
          }
        },
        "additionalProperties": false
      },
      "CreatePedidoDto": {
        "required": [
          "clienteId",
          "detalles",
          "fecha"
        ],
        "type": "object",
        "properties": {
          "clienteId": {
            "type": "integer",
            "format": "int32"
          },
          "fecha": {
            "type": "string",
            "format": "date-time"
          },
          "observaciones": {
            "type": "string",
            "nullable": true
          },
          "detalles": {
            "minItems": 1,
            "type": "array",
            "items": {
              "$ref": "#/components/schemas/CreateDetallePedidoDto"
            }
          }
        },
        "additionalProperties": false
      },
      "DetallePedidoDto": {
        "type": "object",
        "properties": {
          "detallePedidoId": {
            "type": "integer",
            "format": "int32"
          },
          "productoId": {
            "type": "integer",
            "format": "int32"
          },
          "productoNombre": {
            "type": "string",
            "nullable": true
          },
          "cantidad": {
            "type": "integer",
            "format": "int32"
          },
          "precioUnitario": {
            "type": "number",
            "format": "double"
          },
          "costoUnitario": {
            "type": "number",
            "format": "double"
          },
          "subtotal": {
            "type": "number",
            "format": "double"
          },
          "rentabilidadPorcentaje": {
            "type": "number",
            "format": "double"
          }
        },
        "additionalProperties": false
      },
      "PedidoDto": {
        "type": "object",
        "properties": {
          "pedidoId": {
            "type": "integer",
            "format": "int32"
          },
          "clienteId": {
            "type": "integer",
            "format": "int32"
          },
          "clienteNombre": {
            "type": "string",
            "nullable": true
          },
          "fecha": {
            "type": "string",
            "format": "date-time"
          },
          "total": {
            "type": "number",
            "format": "double"
          },
          "rentabilidadPromedio": {
            "type": "number",
            "format": "double"
          },
          "indicadorRentabilidad": {
            "type": "string",
            "nullable": true
          },
          "estado": {
            "type": "string",
            "nullable": true
          },
          "observaciones": {
            "type": "string",
            "nullable": true
          },
          "detalles": {
            "type": "array",
            "items": {
              "$ref": "#/components/schemas/DetallePedidoDto"
            },
            "nullable": true
          }
        },
        "additionalProperties": false
      },
      "ProductoDto": {
        "type": "object",
        "properties": {
          "productoId": {
            "type": "integer",
            "format": "int32"
          },
          "nombre": {
            "type": "string",
            "nullable": true
          },
          "descripcion": {
            "type": "string",
            "nullable": true
          },
          "costo": {
            "type": "number",
            "format": "double"
          },
          "precioVenta": {
            "type": "number",
            "format": "double"
          },
          "stock": {
            "type": "integer",
            "format": "int32"
          },
          "categoria": {
            "type": "string",
            "nullable": true
          },
          "activo": {
            "type": "boolean"
          },
          "rentabilidadPorcentaje": {
            "type": "number",
            "format": "double"
          }
        },
        "additionalProperties": false
      },
      "UpdatePedidoDto": {
        "required": [
          "clienteId",
          "detalles",
          "fecha"
        ],
        "type": "object",
        "properties": {
          "clienteId": {
            "type": "integer",
            "format": "int32"
          },
          "fecha": {
            "type": "string",
            "format": "date-time"
          },
          "estado": {
            "type": "string",
            "nullable": true
          },
          "observaciones": {
            "type": "string",
            "nullable": true
          },
          "detalles": {
            "minItems": 1,
            "type": "array",
            "items": {
              "$ref": "#/components/schemas/CreateDetallePedidoDto"
            }
          }
        },
        "additionalProperties": false
      }
    }
  }
}